<Incident xmlns:xsi="http://www.w3.org/2001/XMLSchema-instance" xsi:noNamespaceSchemaLocation="file:///C:/DATA/EJS/SVN_Root/Ejustice/trunk/XMLTransformations/OnlineRMSInternalToIncident/IAOnlineRMSIncidentImport.xsd">
   <IncidentReportNum>23-MSP-025282</IncidentReportNum>
   <AgencyCode>63</AgencyCode>
   <ORINum>MDMSP0400</ORINum>
   <ReportDate>07/15/2023 10:11:00</ReportDate>
   <ReportTime>07/15/2023 10:11:00</ReportTime>
   <StartDate>07/15/2023 09:48:00</StartDate>
   <StartTime>07/15/2023 09:48:00</StartTime>
   <Summary>Pedestrian leads to Emergency petition.</Summary>
   <CreatorId>MSP</CreatorId>
   <CreatorDate>07/15/2023 10:11:36</CreatorDate>
   <UpdatorId>MSP5364</UpdatorId>
   <UpdatorDate>10/05/2023 11:22:29</UpdatorDate>
   <IncidentType>
      <IncidentTypeCode>EP</IncidentTypeCode>
   </IncidentType>
   <IncidentAddress>
      <AddressId>696012</AddressId>
      <CreatorId>MSP</CreatorId>
      <CreatorDate>07/15/2023 10:11:37</CreatorDate>
      <UpdatorId>MSP</UpdatorId>
      <UpdatorDate>07/16/2023 22:19:52</UpdatorDate>
      <Address>
         <AddressId>696012</AddressId>
         <StreetDirCode>W</StreetDirCode>
         <StreetName>I-495</StreetName>
         <StreetTypeCode>HWY</StreetTypeCode>
         <City>Silver Spring</City>
         <StateCode>MD</StateCode>
         <Zip5>20901</Zip5>
         <CountryCode>US</CountryCode>
         <CrossStreetTypeCode>BLVD</CrossStreetTypeCode>
         <Longitude>-76.99818</Longitude>
         <Latitude>39.0166</Latitude>
      </Address>
   </IncidentAddress>
   <IncidentSupplement>
      <SupplementSequence>0</SupplementSequence>
      <IncSupplementStatusCode>A</IncSupplementStatusCode>
      <SuppReportDate>07/15/2023 10:11:34</SuppReportDate>
      <SuppReportTime>07/15/2023 10:11:34</SuppReportTime>
      <AgencyOnly>N</AgencyOnly>
      <SecurityLevel>1100</SecurityLevel>
      <SuppAgencyCode>63</SuppAgencyCode>
      <UnknownNoOffenders>N</UnknownNoOffenders>
      <DsIcrDate>07/23/2023 23:56:16</DsIcrDate>
      <DsIcrSubmissionStatus>NOT REPORTABLE</DsIcrSubmissionStatus>
      <CreatorId>MSP</CreatorId>
      <CreatorDate>07/15/2023 10:11:36</CreatorDate>
      <UpdatorId>MSP5995</UpdatorId>
      <UpdatorDate>07/23/2023 23:56:17</UpdatorDate>
      <IncidentSuppNarrative>
         <NarrativeNumber>1</NarrativeNumber>
         <NarrativeTitle>Original Narrative</NarrativeTitle>
         <NarrativeText>On July 15, 2023 at approximately 0948 hours, I, Trooper First Class Emerick #6888, was dispatched to the Outer Loop of I-495 prior to University Boulevard in Silver Spring, Montgomery County, Maryland for a pedestrian on the highway. As I was en route, I was advised that the pedestrian was a black male wearing a white shirt and gray sweatpants, and that the pedestrian was looking over the edge of a bridge. I arrived on scene and the pedestrian was just past the bridge over the Northwest Branch Anacostia River. I recognized the man to be a subject that I had dealt with a few days prior. The man was walking west, away from my patrol vehicle. I began yelling the mans name to get him to stop. The man kept walking, I got in front of the man and got him to stop. I recognized the man from two days prior to be Martin Douglass Harris III (Black/Male DOB 11/17/1979).   I asked Harris if he remembered me from the other day. Harris shook his head no. I continued to try to converse with Harris, and he continued to stare forward into space. I asked Harris if he wanted to be checked out by EMS and he shook his head no. I again tried to converse with Harris and he stared into space. I asked Harris if he wanted to go to the hospital and he shook his head no. I then tried to converse with Harris again, to which he stared into space and would not acknowledge me. Due to Harris mental state of not being able or wanting to answer simple questions, in addition to multiple callers stating he was looking over the bridge, I believed that Harris may be a danger to himself. I then placed Harris into handcuffs and placed him in the front seat of my patrol vehicle. I was taking Harris to Suburban Hospital for an Emergency Petition. After I placed Harris into my vehicle he began to converse with me.    Harris asked me what I was, he stated that I had to be something to be able to stop him. While en route to the hospital Harris stated that I couldnt drop him off in a nice neighborhood, but I would drop him off in a neighborhood with people like him so he could kill them. Harris stated that he saw a couple traps and was hoping the traps would go off. Harris asked me if I could kill him and take this power.  Once at Suburban Hospital, Emergency Petition paperwork was filled out and give to hospital staff. Harris was issued a warning for walking on the highway. Care and Custody of Harris was transferred to Suburban Hospital Staff.  Case closed by Emergency petition. </NarrativeText>
         <CreatorId>MSP6888</CreatorId>
         <CreatorDate>07/16/2023 22:25:33</CreatorDate>
         <UpdatorId>MSP6888</UpdatorId>
         <UpdatorDate>07/21/2023 05:03:05</UpdatorDate>
      </IncidentSuppNarrative>
      <IncidentOfficer>
         <OfficerRoleCode>H</OfficerRoleCode>
         <Officer>
            <AgencyCode>63</AgencyCode>
            <ORINumber>MDMSP0400</ORINumber>
            <LastName>Emerick</LastName>
            <FirstName>Seth</FirstName>
            <InternalID>6888</InternalID>
         </Officer>
      </IncidentOfficer>
      <IncidentOfficer>
         <OfficerRoleCode>P</OfficerRoleCode>
         <Officer>
            <AgencyCode>63</AgencyCode>
            <ORINumber>MDMSP0400</ORINumber>
            <LastName>Moore</LastName>
            <FirstName>Tyler</FirstName>
            <InternalID>5995</InternalID>
         </Officer>
      </IncidentOfficer>
      <IncidentOfficer>
         <OfficerRoleCode>R</OfficerRoleCode>
         <Officer>
            <AgencyCode>63</AgencyCode>
            <ORINumber>MDMSP0400</ORINumber>
            <LastName>Emerick</LastName>
            <FirstName>Seth</FirstName>
            <InternalID>6888</InternalID>
         </Officer>
      </IncidentOfficer>
      <IncidentOfficer>
         <OfficerRoleCode>X</OfficerRoleCode>
         <Officer>
            <AgencyCode>63</AgencyCode>
            <ORINumber>MDMSP0400</ORINumber>
            <LastName>Emerick</LastName>
            <FirstName>Seth</FirstName>
            <InternalID>6888</InternalID>
         </Officer>
      </IncidentOfficer>
      <IncidentOffense>
         <IncidentId>514724</IncidentId>
         <OffenseNumber>1</OffenseNumber>
         <OffenseStatusCode>05</OffenseStatusCode>
         <OffenseCode>16996</OffenseCode>
         <PlaceCode>13</PlaceCode>
         <BiasCode>88</BiasCode>
         <SupplementSeq>0</SupplementSeq>
         <UCRNumber>1</UCRNumber>
         <OffenseStatusDate>07/15/2023 22:22:00</OffenseStatusDate>
         <CreatorId>MSP6888</CreatorId>
         <CreatorDate>07/16/2023 22:21:48</CreatorDate>
         <UpdatorId>MSP6888</UpdatorId>
         <UpdatorDate>07/16/2023 22:22:52</UpdatorDate>
      </IncidentOffense>
      <IncidentPerson>
         <ApproxAge>43</ApproxAge>
         <ResidentStatusCode>O</ResidentStatusCode>
         <CreatorId>MSP6888</CreatorId>
         <CreatorDate>07/16/2023 22:21:49</CreatorDate>
         <UpdatorId>MSP</UpdatorId>
         <UpdatorDate>08/01/2023 01:57:09</UpdatorDate>
         <Person>
            <PersonId>257497</PersonId>
            <RaceCode>B</RaceCode>
            <SexCode>M</SexCode>
            <EthnicityCode>N</EthnicityCode>
            <PersonVerified>Y</PersonVerified>
            <PersonPrimaryName>
               <LastName>Harris</LastName>
               <FirstName>Martin</FirstName>
               <MiddleName>Douglass</MiddleName>
               <DOB>11/17/1979 00:00:00</DOB>
               <SSN>5.77041453E8</SSN>
               <TitleCode>III</TitleCode>
               <DateOfInfo>01/06/2020 02:05:44</DateOfInfo>
               <SLastName>H620</SLastName>
               <SFirstName>M635</SFirstName>
            </PersonPrimaryName>
            <Alias>
               <NameTypeCode>P</NameTypeCode>
               <LastName>Harris</LastName>
               <FirstName>Martin</FirstName>
               <MiddleName>Douglass</MiddleName>
               <DOB>11/17/1979 00:00:00</DOB>
               <SSN>5.77041453E8</SSN>
               <TitleCode>III</TitleCode>
               <SLastName>H620</SLastName>
               <SFirstName>M635</SFirstName>
               <DateOfInfo>01/06/2020 02:05:44</DateOfInfo>
            </Alias>
            <PersonAddress>
               <StreetNumber>13009</StreetNumber>
               <StreetName>Margot</StreetName>
               <StreetTypeCode>DR</StreetTypeCode>
               <City>Rockville</City>
               <StateCode>MD</StateCode>
               <Zip5>20853</Zip5>
               <Zip4>3719</Zip4>
               <CountryCode>US</CountryCode>
               <CountyCode>NaN</CountyCode>
               <Longitude>-77.101164</Longitude>
               <Latitude>39.0696058</Latitude>
            </PersonAddress>
            <PersonAddress>
               <StreetNumber>2213</StreetNumber>
               <StreetName>Rhode Island </StreetName>
               <StreetTypeCode>AVE</StreetTypeCode>
               <SubTypeCode>APT</SubTypeCode>
               <SubNumber>4</SubNumber>
               <City>Washington </City>
               <StateCode>DC</StateCode>
               <Zip5>20018</Zip5>
               <CountryCode>US</CountryCode>
               <Longitude>-76.973724</Longitude>
               <Latitude>38.930019</Latitude>
            </PersonAddress>
         </Person>
         <IncidentPersonRole>
            <RoleType>PE</RoleType>
            <CreatorId>MSP6888</CreatorId>
            <CreatorDate>07/16/2023 22:24:01</CreatorDate>
            <UpdatorId>MSP</UpdatorId>
            <UpdatorDate>12/05/2023 01:49:07</UpdatorDate>
         </IncidentPersonRole>
         <IncidentPersonRole>
            <RoleType>S</RoleType>
            <CreatorId>MSP6888</CreatorId>
            <CreatorDate>07/16/2023 22:24:01</CreatorDate>
            <UpdatorId>MSP</UpdatorId>
            <UpdatorDate>12/05/2023 01:49:07</UpdatorDate>
         </IncidentPersonRole>
      </IncidentPerson>
   </IncidentSupplement>
</Incident>