<Incident xmlns:xsi="http://www.w3.org/2001/XMLSchema-instance" xsi:noNamespaceSchemaLocation="file:///C:/DATA/EJS/SVN_Root/Ejustice/trunk/XMLTransformations/OnlineRMSInternalToIncident/IAOnlineRMSIncidentImport.xsd">
   <IncidentReportNum>23-MSP-039182</IncidentReportNum>
   <AgencyCode>40O</AgencyCode>
   <ORINum>MDMSP9800</ORINum>
   <ReportDate>11/06/2023 11:41:00</ReportDate>
   <ReportTime>11/06/2023 11:41:00</ReportTime>
   <StartDate>10/07/2023 11:40:00</StartDate>
   <StartTime>10/07/2023 11:40:00</StartTime>
   <EndDate>10/14/2023 12:38:00</EndDate>
   <Summary>fraud</Summary>
   <CreatorId>MSP</CreatorId>
   <CreatorDate>11/06/2023 11:41:30</CreatorDate>
   <UpdatorId>MSP6049</UpdatorId>
   <UpdatorDate>11/20/2023 13:35:09</UpdatorDate>
   <IncidentType>
      <IncidentTypeCode>FRD</IncidentTypeCode>
   </IncidentType>
   <IncidentAddress>
      <AddressId>712490</AddressId>
      <CreatorId>MSP</CreatorId>
      <CreatorDate>11/06/2023 11:41:31</CreatorDate>
      <UpdatorId>MSP</UpdatorId>
      <UpdatorDate>11/08/2023 13:09:03</UpdatorDate>
      <Address>
         <AddressId>712490</AddressId>
         <StreetNumber>10 </StreetNumber>
         <StreetName>Furnace </StreetName>
         <StreetTypeCode>CT</StreetTypeCode>
         <City>Cockeysville</City>
         <StateCode>MD</StateCode>
         <Zip5>21030</Zip5>
         <CountryCode>US</CountryCode>
         <Longitude>-76.640219</Longitude>
         <Latitude>39.496272</Latitude>
      </Address>
   </IncidentAddress>
   <IncidentSupplement>
      <SupplementSequence>0</SupplementSequence>
      <IncSupplementStatusCode>A</IncSupplementStatusCode>
      <SuppReportDate>11/06/2023 11:41:29</SuppReportDate>
      <SuppReportTime>11/06/2023 11:41:29</SuppReportTime>
      <AgencyOnly>N</AgencyOnly>
      <SecurityLevel>1100</SecurityLevel>
      <SuppAgencyCode>40O</SuppAgencyCode>
      <DsIcrDate>11/20/2023 13:35:08</DsIcrDate>
      <DsIcrSubmissionStatus>NOT REPORTABLE</DsIcrSubmissionStatus>
      <CreatorId>MSP</CreatorId>
      <CreatorDate>11/06/2023 11:41:30</CreatorDate>
      <UpdatorId>MSP6049</UpdatorId>
      <UpdatorDate>11/20/2023 13:35:09</UpdatorDate>
      <IncidentSuppNarrative>
         <NarrativeNumber>1</NarrativeNumber>
         <NarrativeTitle>Original Narrative</NarrativeTitle>
         <NarrativeText>On November 7th, 2023, M/Tpr Kelly Jaskiewicz of the Northern Region Criminal Investigation Division responded to 10 Furnace Ct, Cockeysville, MD 21030 for a reported fraud. The victims Jane Trommatter advised she was scammed out of approximately $3,000.00 while attempting to purchase a dog online. Jane had been searching for a new dog as her older dog was in the process of dying. Jane was convinced to get a dog by a priest she helps to take care of, although she did not think she was ready for one yet. Jane had previously provided copies of emails and screenshots of the text conversations she had along with proof of the money she sent to Cpl Hall. Review of the information provided shows that Jane sent the money through numerous money applications (money gram, Zelle, PayPal) and even utilized her credit card. The suspect(s) used several phone numbers, names and emails to complete the elaborate scam. Full review of the information provided shows that Jane paid $3,200.93 for a dog she never received. The communication ended with the suspect(s) advising the dog was being sent to quarantine law court due to her failure to comply with the vaccine requirements.  I requested Jane to show me her bank account and the money she paid. Jane showed me four payments delivered. Two payments were completed on 10-11-2023 to Brya Galloway for a total of $1,599.00. These payments were completed through Zelle. Two additional payments were completed on 10-10-2023to Cynthia Akuchia for a total of $650.00 completed through Zelle. After review of the documents provided I showed Jane a document with a payment that appeared to be through MasterCard utilizing the PayPal application. Jane pulled up the account and showed me how $951.93 was paid to Liam Shaw on 10-11-2023. It appears this money was converted into pounds.  I have identified additional investigative leads to follow up on from the information provided to me from the victim: PETS SELLER Elizabeth F. Kraus 1230 Fording Island Rd. Bluffton, SC 29910, (515)850-2147 elizabethfkraus@gmail.com  PayPal- shawliam715 4029357733 CA 95131 USA , shawliam382@gmail.com  EMAIL contact - info.globalpetslogistics@gmail.com  Listed as USA branch - Mark William, 11818 Riverside Dr. Ste 118 Valley Village, CA 91607, 707-706-0764, 760-502-0830, 887-202-7698  Brya Galloway- Recipient token- 470-361-6708 also 470-361-4768  Glenillia Galloway- 6197123114 number to use for Zelle  Number associated with the tracking- (864)865-6088  Sent money on Money Gram- Micheal Touli- 3401 38th St. NW Apt 202, Washington DC, 20016  address provided by 864-865-6088- 405 Christopher Ave, APT 9  MONEY GRAM transfer reference # 24995371  Seller phone number that texted victim- (515)850-2147  Cynthia Akuchie- 2407023983 (possible phone number) also used on Zelle.  Phone number that texted victim about shipping puppy- (864) 865-6088  Jasmine Morales 2028308332 (possible phone number) used for Zelle  I have contacted Baltimore County States Attorney office to review the case facts.  Case open pending additional information</NarrativeText>
         <CreatorId>MSP5458</CreatorId>
         <CreatorDate>11/08/2023 12:42:14</CreatorDate>
         <UpdatorId>MSP5458</UpdatorId>
         <UpdatorDate>11/13/2023 13:47:40</UpdatorDate>
      </IncidentSuppNarrative>
      <IncidentOfficer>
         <OfficerRoleCode>P</OfficerRoleCode>
         <Officer>
            <AgencyCode>40O</AgencyCode>
            <ORINumber>MDMSP9800</ORINumber>
            <LastName>Donald</LastName>
            <FirstName>Frank</FirstName>
            <InternalID>6049</InternalID>
         </Officer>
      </IncidentOfficer>
      <IncidentOfficer>
         <OfficerRoleCode>R</OfficerRoleCode>
         <Officer>
            <AgencyCode>40O</AgencyCode>
            <ORINumber>MDMSP9800</ORINumber>
            <LastName>Jaskiewicz</LastName>
            <FirstName>Kelly</FirstName>
            <InternalID>5458</InternalID>
         </Officer>
      </IncidentOfficer>
      <IncidentPerson>
         <ApproxAge>00</ApproxAge>
         <ResidentStatusCode>R</ResidentStatusCode>
         <CreatorId>MSP5458</CreatorId>
         <CreatorDate>11/08/2023 12:41:06</CreatorDate>
         <UpdatorId>MSP</UpdatorId>
         <UpdatorDate>11/08/2023 13:09:03</UpdatorDate>
         <Person>
            <PersonId>392460</PersonId>
            <RaceCode>W</RaceCode>
            <SexCode>F</SexCode>
            <EthnicityCode>N</EthnicityCode>
            <PersonVerified>Y</PersonVerified>
            <PersonPrimaryName>
               <LastName>Trommatter</LastName>
               <DateOfInfo>11/08/2023 12:40:53</DateOfInfo>
               <SLastName>T653</SLastName>
            </PersonPrimaryName>
            <Alias>
               <NameTypeCode>P</NameTypeCode>
               <LastName>Trommatter</LastName>
               <SLastName>T653</SLastName>
               <DateOfInfo>11/08/2023 12:40:53</DateOfInfo>
            </Alias>
            <PersonAddress>
               <StreetNumber>10 </StreetNumber>
               <StreetName>Furnace </StreetName>
               <StreetTypeCode>CT</StreetTypeCode>
               <City>Cockeysville</City>
               <StateCode>MD</StateCode>
               <Zip5>21030</Zip5>
               <CountryCode>US</CountryCode>
               <CountyCode>NaN</CountyCode>
               <Longitude>-76.640219</Longitude>
               <Latitude>39.496272</Latitude>
            </PersonAddress>
            <PersonPhone>
               <PhoneTypeCode>CEL</PhoneTypeCode>
               <PhoneArea>443</PhoneArea>
               <PhonePrefix>286</PhonePrefix>
               <PhoneSuffix>3359</PhoneSuffix>
               <DateOfInfo>11/08/2023 00:00:00</DateOfInfo>
            </PersonPhone>
         </Person>
         <IncidentPersonRole>
            <RoleType>V</RoleType>
            <CreatorId>MSP5458</CreatorId>
            <CreatorDate>11/08/2023 12:41:06</CreatorDate>
            <UpdatorId>MSP</UpdatorId>
            <UpdatorDate>12/05/2023 01:49:29</UpdatorDate>
         </IncidentPersonRole>
      </IncidentPerson>
   </IncidentSupplement>
</Incident>