<?xml version="1.0" encoding="UTF-8"?>
<Incident xmlns:xsi="http://www.w3.org/2001/XMLSchema-instance"
          xsi:noNamespaceSchemaLocation="file:///C:/DATA/EJS/SVN_Root/Ejustice/trunk/XMLTransformations/OnlineRMSInternalToIncident/IAOnlineRMSIncidentImport.xsd">
   <IncidentReportNum>23-MSP-044350</IncidentReportNum>
   <AgencyCode>61</AgencyCode>
   <ORINum>MDMSP5600</ORINum>
   <ReportDate>12/15/2023 17:30:00</ReportDate>
   <ReportTime>12/15/2023 17:30:00</ReportTime>
   <StartDate>12/15/2023 17:05:00</StartDate>
   <StartTime>12/15/2023 17:05:00</StartTime>
   <Summary>ACRS</Summary>
   <CreatorId>MSP</CreatorId>
   <CreatorDate>12/15/2023 17:30:55</CreatorDate>
   <UpdatorId>MSP5368</UpdatorId>
   <UpdatorDate>12/27/2023 03:20:20</UpdatorDate>
   <IncidentType>
      <IncidentTypeCode>ACC</IncidentTypeCode>
   </IncidentType>
   <IncidentAddress>
      <IncAddrComment>BRANCH AVE SB TO OLD BRANCH AVE/ KIRBY RD</IncAddrComment>
      <AddressId>593135</AddressId>
      <CreatorId>MSP</CreatorId>
      <CreatorDate>12/15/2023 17:30:56</CreatorDate>
      <UpdatorId>MSP</UpdatorId>
      <UpdatorDate>12/27/2023 02:51:03</UpdatorDate>
      <Address>
         <AddressId>593135</AddressId>
         <StreetName>Branch Ave Sb To Old Branch</StreetName>
         <StreetTypeCode>AVE</StreetTypeCode>
         <City>Clinton</City>
         <StateCode>MD</StateCode>
         <CountryCode>US</CountryCode>
         <CrossStreetTypeCode>RD</CrossStreetTypeCode>
         <AddressCommonName>
            <CommonPlaceName>S5 / KIRBY</CommonPlaceName>
         </AddressCommonName>
         <AddressCommonName>
            <CommonPlaceName>0-0 BRANCH AVE SB TO OLD BRANCH AVE / 6200-6397 KIRBY RD</CommonPlaceName>
         </AddressCommonName>
      </Address>
   </IncidentAddress>
   <IncidentSupplement>
      <SupplementSequence>0</SupplementSequence>
      <IncSupplementStatusCode>A</IncSupplementStatusCode>
      <SuppReportDate>12/15/2023 17:30:52</SuppReportDate>
      <SuppReportTime>12/15/2023 17:30:52</SuppReportTime>
      <AgencyOnly>N</AgencyOnly>
      <SecurityLevel>1100</SecurityLevel>
      <SuppAgencyCode>61</SuppAgencyCode>
      <DsIcrDate>12/27/2023 03:20:20</DsIcrDate>
      <DsIcrSubmissionStatus>NOT REPORTABLE</DsIcrSubmissionStatus>
      <CreatorId>MSP</CreatorId>
      <CreatorDate>12/15/2023 17:30:55</CreatorDate>
      <UpdatorId>MSP5368</UpdatorId>
      <UpdatorDate>12/27/2023 03:20:20</UpdatorDate>
      <IncidentSuppNarrative>
         <NarrativeNumber>1</NarrativeNumber>
         <NarrativeTitle>Original Narrative</NarrativeTitle>
         <NarrativeText>ACRS SUBMITTED IN DELTA PLUS.&amp;nbsp;</NarrativeText>
         <CreatorId>MSP6534</CreatorId>
         <CreatorDate>12/27/2023 02:51:23</CreatorDate>
         <UpdatorId>MSP6534</UpdatorId>
         <UpdatorDate>12/27/2023 02:51:23</UpdatorDate>
      </IncidentSuppNarrative>
      <IncidentOfficer>
         <OfficerRoleCode>P</OfficerRoleCode>
         <Officer>
            <AgencyCode>61</AgencyCode>
            <ORINumber>MDMSP5600</ORINumber>
            <LastName>Sorenson</LastName>
            <FirstName>Bryan</FirstName>
            <InternalID>5368</InternalID>
         </Officer>
      </IncidentOfficer>
      <IncidentOfficer>
         <OfficerRoleCode>R</OfficerRoleCode>
         <Officer>
            <AgencyCode>61</AgencyCode>
            <ORINumber>MDMSP5600</ORINumber>
            <LastName>Butt</LastName>
            <FirstName>Mohammad</FirstName>
            <InternalID>6534</InternalID>
         </Officer>
      </IncidentOfficer>
   </IncidentSupplement>
</Incident>